README.md
setup.cfg
setup.py
businessplots/__init__.py
businessplots/_data.py
businessplots/_limits.py
businessplots/_overlap.py
businessplots/_style.py
businessplots/_text.py
businessplots/arrows.py
businessplots/axis.py
businessplots/formatters.py
businessplots/title.py
businessplots.egg-info/PKG-INFO
businessplots.egg-info/SOURCES.txt
businessplots.egg-info/dependency_links.txt
businessplots.egg-info/not-zip-safe
businessplots.egg-info/requires.txt
businessplots.egg-info/top_level.txt