Metadata-Version: 1.1
Name: businessplots
Version: 0.2
Summary: A Python / Matplotlib toolkit to quickly draw business & consulting-style quality plots.
Home-page: https://github.com/fvinas/businessplots
Author: Fabien Vinas
Author-email: fabien.vinas@gmail.com
License: UNKNOWN
Download-URL: https://github.com/fvinas/businessplots/archive/0.2.tar.gz
Platform: UNKNOWN
